bonded/__init__.py
bonded/__main__.py
bonded/_importlib.py
bonded/_internal.py
bonded/_sys.py
bonded/bonded.py
bonded/display.py
bonded/evaluation.py
bonded/executable_inspection.py
bonded/module_inspection.py
bonded/package_inspection.py
bonded/settings.py
bonded-0.5b1.dist-info/entry_points.txt
bonded-0.5b1.dist-info/LICENSE
bonded-0.5b1.dist-info/WHEEL
bonded-0.5b1.dist-info/METADATA
bonded-0.5b1.dist-info/RECORD
