Metadata-Version: 2.1
Name: bonded
Version: 0.5b1
Summary: Have your imports passed inspection?
Keywords: linter,imports,project,metadata
Author-email: Jeremiah Paige <ucodery@gmail.com>
Classifier: License :: OSI Approved :: MIT License
Requires-Dist: importlib-metadata>=4.7,!=6.1
Requires-Dist: packaging
Requires-Dist: rich
Requires-Dist: tomli
Requires-Dist: flit ; extra == "dev"
Requires-Dist: tox ; extra == "dev"
Requires-Dist: blue ; extra == "lint"
Requires-Dist: pyproject-flake8 ; extra == "lint"
Requires-Dist: usort ; extra == "lint"
Requires-Dist: pytest >=2.7.3 ; extra == "test"
Project-URL: Home, https://github.com/ucodery/bonded
Provides-Extra: dev
Provides-Extra: lint
Provides-Extra: test
